pgi_logging/__init__.py
pgi_logging/utils.py
pgi_logging/pgi_handlers/__init__.py
pgi_logging/pgi_handlers/tk.py
pgi_logging-0.3.1.dist-info/METADATA
pgi_logging-0.3.1.dist-info/WHEEL
pgi_logging-0.3.1.dist-info/RECORD
