Metadata-Version: 2.3
Name: pgi-logging
Version: 0.3.1
Project-URL: homepage, https://bitbucket.org/pathwaysgi/pgi-logging
Author-email: Christopher Endres <cmendres@pathwaysgi.com>
Requires-Python: <3.12,>=3.7
Requires-Dist: cloudpathlib
Requires-Dist: colorlog
Requires-Dist: pydantic
